django_profiler_vmprof/__init__.py
django_profiler_vmprof/middleware.py
django_profiler_vmprof/models.py
django_profiler_vmprof/urls.py
django_profiler_vmprof/views.py
django_profiler_vmprof/migrations/0001_initial.py
django_profiler_vmprof/migrations/0002_auto_20171018_2028.py
django_profiler_vmprof/migrations/0003_auto_20171229_2027.py
django_profiler_vmprof/migrations/0004_requestprofile_depth.py
django_profiler_vmprof/migrations/0005_remove_requestprofile_depth.py
django_profiler_vmprof/migrations/0006_auto_20180227_1733.py
django_profiler_vmprof/migrations/0007_requestprofile_peak_rss_use.py
django_profiler_vmprof/migrations/__init__.py
django_profiler_vmprof/static/vmprof/compat.js
django_profiler_vmprof/static/vmprof/details.html
django_profiler_vmprof/static/vmprof/index.html
django_profiler_vmprof/static/vmprof/list.html
django_profiler_vmprof/static/vmprof/main.css
django_profiler_vmprof/static/vmprof/main.js
django_profiler_vmprof/static/vmprof/stats.js
django_profiler_vmprof/static/vmprof/visualizations.js
django_profiler_vmprof/static/vmprof/images/cpython.png
django_profiler_vmprof/static/vmprof/images/loader.gif
django_profiler_vmprof/static/vmprof/images/logo.png
django_profiler_vmprof/static/vmprof/images/logo_150.png
django_profiler_vmprof/static/vmprof/images/pypy.png
django_profiler_vmprof/static/vmprof/images/vmprof-logo-big.png
django_profiler_vmprof/static/vmprof/images/vmprof-logo.png
django_profiler_vmprof/static/vmprof/libs/angular-cookies.min.js
django_profiler_vmprof/static/vmprof/libs/angular-resource.min.js
django_profiler_vmprof/static/vmprof/libs/angular-route.min.js
django_profiler_vmprof/static/vmprof/libs/angular-sanitize.min.js
django_profiler_vmprof/static/vmprof/libs/angular.min.js
django_profiler_vmprof/static/vmprof/libs/d3.min.js
django_profiler_vmprof/static/vmprof/libs/jquery-2.1.1.min.js
django_profiler_vmprof/static/vmprof/libs/jsrender.min.js
django_profiler_vmprof/static/vmprof/libs/lodash.min.js
django_profiler_vmprof-0.3.5.dist-info/LICENSE
django_profiler_vmprof-0.3.5.dist-info/METADATA
django_profiler_vmprof-0.3.5.dist-info/WHEEL
django_profiler_vmprof-0.3.5.dist-info/top_level.txt
django_profiler_vmprof-0.3.5.dist-info/RECORD
