Metadata-Version: 2.1
Name: django-profiler-vmprof
Version: 0.3.5
Summary: A minimalist VMProf integration for Django.
Home-page: https://github.com/bawr/django-profiler-vmprof
Author: Bartosz Wróblewski
Author-email: bawr@hszm.pl
License: MIT License
Platform: UNKNOWN
Classifier: Environment :: Web Environment
Classifier: Framework :: Django
Classifier: Framework :: Django :: 2.0
Classifier: Intended Audience :: Developers
Classifier: License :: OSI Approved :: MIT License
Classifier: Operating System :: POSIX
Classifier: Programming Language :: Python
Classifier: Programming Language :: Python :: 3
Classifier: Programming Language :: Python :: 3.6
Classifier: Programming Language :: Python :: 3.7
Requires-Python: ~=3.6
Requires-Dist: django (>=2.0)
Requires-Dist: psutil (>=5.2.1)
Requires-Dist: vmprof (>=0.4.9)
